torch_choice/__init__.py
torch_choice/data/__init__.py
torch_choice/data/choice_dataset.py
torch_choice/data/example_datasets.py
torch_choice/data/joint_dataset.py
torch_choice/data/utils.py
torch_choice/model/__init__.py
torch_choice/model/coefficient.py
torch_choice/model/conditional_logit_model.py
torch_choice/model/formula_parser.py
torch_choice/model/nested_logit_model.py
torch_choice/utils/__init__.py
torch_choice/utils/easy_data_wrapper.py
torch_choice/utils/run_helper.py
torch_choice/utils/run_helper_lightning.py
torch_choice/utils/std.py
torch_choice-1.0.6.dist-info/LICENSE
torch_choice-1.0.6.dist-info/METADATA
torch_choice-1.0.6.dist-info/WHEEL
torch_choice-1.0.6.dist-info/top_level.txt
torch_choice-1.0.6.dist-info/RECORD
