Metadata-Version: 2.1
Name: torch_choice
Version: 1.0.6
Summary: A Pytorch Backend Library for Choice Modelling
Home-page: https://gsbdbi.github.io/torch-choice/
Author: Tianyu Du, Ayush Kanodia, and Susan Athey
Author-email: tianyudu@stanford.edu
License: MIT
Classifier: License :: OSI Approved :: MIT License
Classifier: Programming Language :: Python :: 3
Classifier: Programming Language :: Python :: 3.8
License-File: LICENSE
Requires-Dist: numpy >=1.22
Requires-Dist: termcolor >=1.1.0
Requires-Dist: scikit-learn
Requires-Dist: pandas >=1.4.3
Requires-Dist: tabulate >=0.8.10
Requires-Dist: torch >=1.12.0
Requires-Dist: pytorch-lightning >=1.6.3
